termfx/__init__.py
termfx/core.py
termfx-1.0.1.dist-info/licenses/LICENSE
termfx-1.0.1.dist-info/METADATA
termfx-1.0.1.dist-info/WHEEL
termfx-1.0.1.dist-info/top_level.txt
termfx-1.0.1.dist-info/RECORD
