Metadata-Version: 2.4
Name: termfx
Version: 1.0.1
Summary: Powerful and beautiful terminal output/input utilities for Python CLI tools.
Home-page: https://github.com/MyArchiveProjects/termfx
Author: MyArchiveProject
License: MIT
Project-URL: Source, https://github.com/MyArchiveProjects/termfx
Project-URL: Issues, https://github.com/MyArchiveProjects/termfx/issues
Keywords: terminal cli print input formatting color styled centered progress bar ascii
Classifier: Development Status :: 5 - Production/Stable
Classifier: Environment :: Console
Classifier: Intended Audience :: Developers
Classifier: Topic :: Software Development :: Libraries :: Python Modules
Classifier: License :: OSI Approved :: MIT License
Classifier: Programming Language :: Python :: 3
Classifier: Operating System :: OS Independent
Requires-Python: >=3.7
License-File: LICENSE
Requires-Dist: colorama
Dynamic: author
Dynamic: classifier
Dynamic: description
Dynamic: description-content-type
Dynamic: home-page
Dynamic: keywords
Dynamic: license
Dynamic: license-file
Dynamic: project-url
Dynamic: requires-dist
Dynamic: requires-python
Dynamic: summary
